{"accounts":[{"account":{"active":true,"allocationHistory":[],"balance":"0","identity":{"address":"N\u0000sourcecred\u0000core\u0000IDENTITY\u00004jsYzwtBUrwlyI5FWa7fbg\u0000","aliases":[{"address":"N\u0000sourcecred\u0000discord\u0000MEMBER\u0000user\u0000747357042062131210\u0000","description":"discord/discord-747357042062131210#7340"}],"id":"4jsYzwtBUrwlyI5FWa7fbg","name":"discord-747357042062131210","subtype":"USER"},"mergedIdentityIds":["4jsYzwtBUrwlyI5FWa7fbg"],"paid":"0","payoutAddresses":{}},"cred":[0.0933405708399565,0.010371183842209879],"totalCred":0.10371175468216638},{"account":{"active":false,"allocationHistory":[],"balance":"0","identity":{"address":"N\u0000sourcecred\u0000core\u0000IDENTITY\u0000G7lZbwBSan2DRKHvW0FGBA\u0000","aliases":[{"address":"N\u0000sourcecred\u0000discord\u0000MEMBER\u0000bot\u00001005506114265300992\u0000","description":"discord/source-cred-for-dao-yaroya#6529"}],"id":"G7lZbwBSan2DRKHvW0FGBA","name":"source-cred-for-dao-yaroya","subtype":"BOT"},"mergedIdentityIds":["G7lZbwBSan2DRKHvW0FGBA"],"paid":"0","payoutAddresses":{}},"cred":[2.0095945641747246,0.22328830614926318],"totalCred":2.2328828703239876},{"account":{"active":true,"allocationHistory":[],"balance":"0","identity":{"address":"N\u0000sourcecred\u0000core\u0000IDENTITY\u0000u0gmR7cYBz2sj2UVXKNxzw\u0000","aliases":[],"id":"u0gmR7cYBz2sj2UVXKNxzw","name":"SourceCred","subtype":"PROJECT"},"mergedIdentityIds":["u0gmR7cYBz2sj2UVXKNxzw"],"paid":"0","payoutAddresses":{}},"cred":[2.13196172593547,0.23688488363417007],"totalCred":2.36884660956964},{"account":{"active":true,"allocationHistory":[],"balance":"0","identity":{"address":"N\u0000sourcecred\u0000core\u0000IDENTITY\u0000oMytMxAuDZfOAy14C2iVLw\u0000","aliases":[{"address":"N\u0000sourcecred\u0000discord\u0000MEMBER\u0000user\u0000436831799692361730\u0000","description":"discord/Matsuoka#1043"}],"id":"oMytMxAuDZfOAy14C2iVLw","name":"Matsuoka","subtype":"USER"},"mergedIdentityIds":["oMytMxAuDZfOAy14C2iVLw"],"paid":"0","payoutAddresses":{}},"cred":[1.135444614276635,10.219004733769928],"totalCred":11.354449348046563},{"account":{"active":true,"allocationHistory":[],"balance":"0","identity":{"address":"N\u0000sourcecred\u0000core\u0000IDENTITY\u00005ndNskLwP9O7owmAkoK10Q\u0000","aliases":[{"address":"N\u0000sourcecred\u0000discord\u0000MEMBER\u0000user\u0000694428018839388190\u0000","description":"discord/shun#2754"}],"id":"5ndNskLwP9O7owmAkoK10Q","name":"shun","subtype":"USER"},"mergedIdentityIds":["5ndNskLwP9O7owmAkoK10Q"],"paid":"0","payoutAddresses":{}},"cred":[1.2398210599862718,11.158393494177103],"totalCred":12.398214554163374},{"account":{"active":true,"allocationHistory":[],"balance":"0","identity":{"address":"N\u0000sourcecred\u0000core\u0000IDENTITY\u0000TNlI8NOWur2MAYWMvOer6w\u0000","aliases":[{"address":"N\u0000sourcecred\u0000discord\u0000MEMBER\u0000user\u0000742038028389974027\u0000","description":"discord/kasugai#5572"}],"id":"TNlI8NOWur2MAYWMvOer6w","name":"kasugai","subtype":"USER"},"mergedIdentityIds":["TNlI8NOWur2MAYWMvOer6w"],"paid":"0","payoutAddresses":{}},"cred":[0.30549427587281736,2.7494496514062368],"totalCred":3.054943927279054},{"account":{"active":true,"allocationHistory":[],"balance":"0","identity":{"address":"N\u0000sourcecred\u0000core\u0000IDENTITY\u0000Z5NLeVGeOK1mJR9hn13Mug\u0000","aliases":[{"address":"N\u0000sourcecred\u0000discord\u0000MEMBER\u0000user\u0000750341467339489352\u0000","description":"discord/sudax#8283"}],"id":"Z5NLeVGeOK1mJR9hn13Mug","name":"sudax","subtype":"USER"},"mergedIdentityIds":["Z5NLeVGeOK1mJR9hn13Mug"],"paid":"0","payoutAddresses":{}},"cred":[0.8174368700782862,7.35693554823303],"totalCred":8.174372418311316},{"account":{"active":true,"allocationHistory":[],"balance":"0","identity":{"address":"N\u0000sourcecred\u0000core\u0000IDENTITY\u0000Igw7Nel2OQZOTj9qVk0XVg\u0000","aliases":[{"address":"N\u0000sourcecred\u0000discord\u0000MEMBER\u0000user\u0000765110930173984769\u0000","description":"discord/chinastsu-fukasawa#1560"}],"id":"Igw7Nel2OQZOTj9qVk0XVg","name":"chinastsu-fukasawa","subtype":"USER"},"mergedIdentityIds":["Igw7Nel2OQZOTj9qVk0XVg"],"paid":"0","payoutAddresses":{}},"cred":[0.3497497415938288,3.1477488608101396],"totalCred":3.4974986024039683},{"account":{"active":true,"allocationHistory":[],"balance":"0","identity":{"address":"N\u0000sourcecred\u0000core\u0000IDENTITY\u000057sp2Xf8h2phyZZgdaKlqA\u0000","aliases":[{"address":"N\u0000sourcecred\u0000discord\u0000MEMBER\u0000user\u0000847858623395659776\u0000","description":"discord/shohe-Booster#3862"}],"id":"57sp2Xf8h2phyZZgdaKlqA","name":"shohe-Booster","subtype":"USER"},"mergedIdentityIds":["57sp2Xf8h2phyZZgdaKlqA"],"paid":"0","payoutAddresses":{}},"cred":[1.2839698971116047,11.555734767665989],"totalCred":12.839704664777594},{"account":{"active":false,"allocationHistory":[],"balance":"0","identity":{"address":"N\u0000sourcecred\u0000core\u0000IDENTITY\u0000WhBYH7JL6Y81sZjF3e72Zg\u0000","aliases":[{"address":"N\u0000sourcecred\u0000discord\u0000MEMBER\u0000user\u0000693077650259968080\u0000","description":"discord/nhiguchi#7910"}],"id":"WhBYH7JL6Y81sZjF3e72Zg","name":"nhiguchi","subtype":"USER"},"mergedIdentityIds":["WhBYH7JL6Y81sZjF3e72Zg"],"paid":"0","payoutAddresses":{}},"cred":[0.8175391674549136,7.3578554783032715],"totalCred":8.175394645758185}],"intervals":[{"endTimeMs":1659830400000,"startTimeMs":1659225600000},{"endTimeMs":1660435200000,"startTimeMs":1659830400000}],"unclaimedAliases":[]}